chunking_pandas/__init__.py
chunking_pandas/benchmark.py
chunking_pandas/core.py
chunking_pandas/visualization.py
chunking_pandas/utils/__init__.py
chunking_pandas/utils/logging.py
chunking_pandas-0.1.8.dist-info/METADATA
chunking_pandas-0.1.8.dist-info/WHEEL
chunking_pandas-0.1.8.dist-info/entry_points.txt
chunking_pandas-0.1.8.dist-info/licenses/LICENSE
chunking_pandas-0.1.8.dist-info/RECORD
