Metadata-Version: 2.4
Name: chunking_pandas
Version: 0.1.8
Summary: A package for experimenting with different data chunking strategies
Project-URL: Homepage, https://github.com/JohnnyTeutonic/ChunkingForPandas
Project-URL: Bug Tracker, https://github.com/JohnnyTeutonic/ChunkingForPandas/issues
Author-email: Jonathan Reich <jonathanreich100@gmail.com>
License-File: LICENSE
Classifier: License :: OSI Approved :: MIT License
Classifier: Operating System :: OS Independent
Classifier: Programming Language :: Python :: 3
Requires-Python: >=3.10
Requires-Dist: gradio>=3.0.0
Requires-Dist: matplotlib>=3.7.0
Requires-Dist: numpy>=1.20.0
Requires-Dist: pandas>=1.5.0
Requires-Dist: pyarrow>=7.0.0
Requires-Dist: pytest>=7.0.0
Requires-Dist: seaborn>=0.12.0
Provides-Extra: dev
Requires-Dist: mypy>=1.0; extra == 'dev'
Requires-Dist: pytest-cov>=4.0; extra == 'dev'
Requires-Dist: pytest>=7.0; extra == 'dev'
Requires-Dist: ruff>=0.1.0; extra == 'dev'
Provides-Extra: docs
Requires-Dist: sphinx-autobuild>=2021.3.14; extra == 'docs'
Requires-Dist: sphinx-rtd-theme>=1.0; extra == 'docs'
Requires-Dist: sphinx>=4.0; extra == 'docs'
